match_expression/__init__.py
match_expression/match.py
match_expression-0.3.1.dist-info/METADATA
match_expression-0.3.1.dist-info/WHEEL
match_expression-0.3.1.dist-info/licenses/LICENSE
match_expression-0.3.1.dist-info/RECORD
