Metadata-Version: 2.4
Name: match-expression
Version: 0.3.1
Summary: A Python implementation of TypeScript's ts-pattern, type-safe pattern matching with an expressive API
Project-URL: Homepage, https://github.com/qodot/match-expression
Project-URL: Bug Tracker, https://github.com/qodot/match-expression/issues
Project-URL: Repository, https://github.com/qodot/match-expression
Author-email: Qodot <qodot@example.com>
License: MIT
License-File: LICENSE
Keywords: exhaustive,functional,match,pattern,pattern-matching,ts-pattern,type-safe,typescript
Classifier: Development Status :: 3 - Alpha
Classifier: Intended Audience :: Developers
Classifier: License :: OSI Approved :: MIT License
Classifier: Programming Language :: Python :: 3
Classifier: Programming Language :: Python :: 3.12
Classifier: Programming Language :: Python :: 3.13
Requires-Python: >=3.12
Provides-Extra: dev
Requires-Dist: pytest-cov>=4.0.0; extra == 'dev'
Requires-Dist: pytest>=7.0.0; extra == 'dev'
